monero_usd_price/__init__.py
monero_usd_price/monero_usd_price.py
monero_usd_price-1.4.0.dist-info/licenses/LICENSE
monero_usd_price-1.4.0.dist-info/METADATA
monero_usd_price-1.4.0.dist-info/WHEEL
monero_usd_price-1.4.0.dist-info/top_level.txt
monero_usd_price-1.4.0.dist-info/RECORD
