Metadata-Version: 2.4
Name: monero_usd_price
Version: 1.4.0
Summary: Monero-USD-Price is an easy way to get the current median or average price of Monero (median is recommended over average, because it less sensitive to outliers.)
Home-page: https://github.com/lukeprofits/Monero-USD-Price
Author: Luke Profits
Classifier: Programming Language :: Python :: 3
Classifier: License :: OSI Approved :: MIT License
Classifier: Operating System :: OS Independent
License-File: LICENSE
Requires-Dist: requests
Dynamic: author
Dynamic: classifier
Dynamic: home-page
Dynamic: license-file
Dynamic: requires-dist
Dynamic: summary
